ckits/__init__.py
ckits/attribute.py
ckits-0.1a1.dist-info/LICENSE
ckits-0.1a1.dist-info/METADATA
ckits-0.1a1.dist-info/WHEEL
ckits-0.1a1.dist-info/top_level.txt
ckits-0.1a1.dist-info/zip-safe
ckits-0.1a1.dist-info/RECORD
