Metadata-Version: 2.1
Name: ckits
Version: 0.1a1
Summary: containers kits
Home-page: https://github.com/podboy/ckits
Author: Mingzhe Zou
Author-email: zoumingzhe@outlook.com
License: GPLv2
Project-URL: Source Code, https://github.com/podboy/ckits
Project-URL: Bug Tracker, https://github.com/podboy/issues
Project-URL: Documentation, https://github.com/podboy/ckits
Keywords: command-line,argparse,argcomplete
Platform: any
Classifier: Programming Language :: Python
Classifier: Programming Language :: Python :: 3
Requires-Python: >=3.8
License-File: LICENSE
